{
  "clientes": [
    {
      "id": 1,
      "nome": "Jessica Ramos",
      "email": "jessica@gmail.com",
      "data": "12/02/2023 até 13/02/2023"
    },
    {
      "id": 2,
      "nome": "Json Santos",
      "email": "json@gmail.com",
      "data": "23/12/2022 até 03/01/2023"
    },
    {
      "id": 3,
      "nome": "Nathalia Rodrigues",
      "email": "nathalia@gmail.com",
      "data": "12/12/2022"
    }
  ],
  "fucionarios": [
    {
      "id": 1,
      "usuario": "carlos123",
      "nome": "Carlos alberto",
      "cpf": 15478965478,
      "turno": "Manhã",
      "funcao": "cozinheiro"
    },
    {
      "id": 2,
      "usuario": "luiza123",
      "nome": "Luiza Costa",
      "cpf": 145678912,
      "turno": "Tarde",
      "funcao": "camareira"
    },
    {
      "id": 3,
      "usuario": "luiz123",
      "nome": "Luiz Costa",
      "cpf": 1459875612,
      "turno": "Noite",
      "funcao": "jardineiro"
    }
  ],
  "cardapio": [
    {
      "id": 1,
      "nome": "Filé-mignon à francesa",
      "descricao": "teste"
    },
    {
      "id": 2,
      "nome": "Bolo de morango",
      "descricao": "teste"
    },
    {
      "id": 3,
      "nome": "Fraldinha com batata-doce",
      "descricao": "teste"
    }
  ]
}
